{
	"friday":[{
				"sponsor": "TBA",
				"talk": "TBA",
				"time": "10:00pm",
				"location": "SEL 5th floor",
				"description": ""
			},
			{
				"sponsor": "TBA",
				"talk": "TBA",
				"time": "11:00pm",
				"location": "SEL 5th floor",
				"description": ""
			}],
	"saturday":[{
				"sponsor": "TBA",
				"talk": "TBA",
				"time": "12:00am",
				"location": "SEL 5th floor",
				"description": ""
			},
			{
				"sponsor": "TBA",
				"talk": "TBA",
				"time": "1:00am",
				"location": "SEL 5th floor",
				"description": ""
			},
			{
				"sponsor": "TBA",
				"talk": "TBA",
				"time": "2:00am",
				"location": "SEL 5th floor",
				"description": ""
			},
			{
				"sponsor": "TBA",
				"talk": "TBA",
				"time": "9:00am",
				"location": "SEL 5th floor",
				"description": ""
			},
			{
				"sponsor": "TBA",
				"talk": "TBA",
				"time": "10:00am",
				"location": "SEL 5th floor",
				"description": ""
			},
			{
				"sponsor": "TBA",
				"talk": "TBA",
				"time": "11:00am",
				"location": "SEL 5th floor",
				"description": ""
			},
			{
				"sponsor": "TBA",
				"talk": "TBA",
				"time": "1:00pm",
				"location": "SEL 5th floor",
				"description": ""
			},
			{
				"sponsor": "TBA",
				"talk": "TBA",
				"time": "2:00pm",
				"location": "SEL 5th floor",
				"description": ""
			},
			{
				"sponsor": "TBA",
				"talk": "TBA",
				"time": "3:00pm",
				"location": "SEL 5th floor",
				"description": ""
			},
			{
				"sponsor": "TBA",
				"talk": "TBA",
				"time": "4:00pm",
				"location": "SEL 5th floor",
				"description": ""
			},
			{
				"sponsor": "TBA",
				"talk": "TBA",
				"time": "5:00pm",
				"location": "SEL 5th floor",
				"description": ""
			},
			{
				"sponsor": "TBA",
				"talk": "TBA",
				"time": "6:00pm",
				"location": "SEL 5th floor",
				"description": ""
			},
			{
				"sponsor": "TBA",
				"talk": "TBA",
				"time": "8:00pm",
				"location": "SEL 5th floor",
				"description": ""
			},
			{
				"sponsor": "TBA",
				"talk": "TBA",
				"time": "11:00pm",
				"location": "SEL 5th floor",
				"description": ""
			},
			],
	"sunday":[{
				"sponsor": "TBA",
				"talk": "TBA",
				"time": "12:00am",
				"location": "SEL 5th floor",
				"description": ""
			},
			{
				"sponsor": "TBA",
				"talk": "TBA",
				"time": "1:00am",
				"location": "SEL 5th floor",
				"description": ""
			}]
}
